{
  "attack_power": "0",
  "attribute_id": 8,
  "card_id": 12169,
  "card_name": "Draco Enfrentamiento",
  "card_name_label": "",
  "card_name_search": "",
  "card_pen_effect": "",
  "card_text": "Muestra 1 Monstruo de Péndulo \"Dracoasesino\" y 1 Monstruo de Péndulo \"Dracoseñor\" en tu Deck, tu adversario elige 1 al azar para que tú lo pongas en tu Zona del Péndulo o Invoques de Modo Especial (tu elección), y añade la otra carta a tu Deck Extra boca arriba. Sólo puedes activar 1 \"Draco Enfrentamiento\" por turno.",
  "defense_power": "0",
  "effect_id": 5,
  "language": "es",
  "legend_type": "",
  "linkmarker": "",
  "linkno": "",
  "min_card_image_id": 1,
  "note": "",
  "other_item_id": 13,
  "pen_scale_l": "",
  "pen_scale_r": "",
  "sales_at": "2016/01/14",
  "species_id": 24,
  "starchip": "0"
}