{
  "attack_power": "0",
  "attribute_id": 8,
  "card_id": 16757,
  "card_name": "Bosque de Flores Perdidas",
  "card_name_label": "",
  "card_name_search": "",
  "card_pen_effect": "",
  "card_text": "Los monstruos que controles equipados con \"Papillon Iluminado por Estrellas\" no son afectados por los efectos activados de tu adversario. Una vez por turno, cuando tu \"Ficha Aventurera\" destruya un monstruo en batalla: puedes robar 1 carta. Una vez por turno, durante tu Main Phase, si el efecto previo fue activado este turno: puedes añadir a tu mano 1 Mágica de Campo en tu Deck o Cementerio que mencione \"Ficha Aventurera\", excepto \"Bosque de Flores Perdidas\".",
  "defense_power": "0",
  "effect_id": 2,
  "language": "es",
  "legend_type": "",
  "linkmarker": "",
  "linkno": "",
  "min_card_image_id": 1,
  "note": "",
  "other_item_id": 13,
  "pen_scale_l": "",
  "pen_scale_r": "",
  "sales_at": "2022/01/27",
  "species_id": 24,
  "starchip": "0"
}