[
  {
    "card_count": 1,
    "card_id": 4064,
    "card_image_id": 1,
    "card_number": "YSD-EN013",
    "language": "en",
    "pack_id": "13304000",
    "rarity_id": 1
  },
  {
    "card_count": 1,
    "card_id": 4272,
    "card_image_id": 1,
    "card_number": "YSD-EN014",
    "language": "en",
    "pack_id": "13304000",
    "rarity_id": 1
  },
  {
    "card_count": 1,
    "card_id": 4317,
    "card_image_id": 1,
    "card_number": "YSD-EN021",
    "language": "en",
    "pack_id": "13304000",
    "rarity_id": 1
  },
  {
    "card_count": 1,
    "card_id": 4345,
    "card_image_id": 1,
    "card_number": "YSD-EN024",
    "language": "en",
    "pack_id": "13304000",
    "rarity_id": 1
  },
  {
    "card_count": 1,
    "card_id": 4352,
    "card_image_id": 1,
    "card_number": "YSD-EN020",
    "language": "en",
    "pack_id": "13304000",
    "rarity_id": 1
  },
  {
    "card_count": 1,
    "card_id": 4434,
    "card_image_id": 1,
    "card_number": "YSD-EN012",
    "language": "en",
    "pack_id": "13304000",
    "rarity_id": 1
  },
  {
    "card_count": 1,
    "card_id": 4546,
    "card_image_id": 1,
    "card_number": "YSD-EN011",
    "language": "en",
    "pack_id": "13304000",
    "rarity_id": 1
  },
  {
    "card_count": 1,
    "card_id": 4753,
    "card_image_id": 1,
    "card_number": "YSD-EN001",
    "language": "en",
    "pack_id": "13304000",
    "rarity_id": 1
  },
  {
    "card_count": 1,
    "card_id": 4803,
    "card_image_id": 1,
    "card_number": "YSD-EN031",
    "language": "en",
    "pack_id": "13304000",
    "rarity_id": 1
  },
  {
    "card_count": 1,
    "card_id": 4835,
    "card_image_id": 1,
    "card_number": "YSD-EN025",
    "language": "en",
    "pack_id": "13304000",
    "rarity_id": 1
  },
  {
    "card_count": 1,
    "card_id": 4849,
    "card_image_id": 1,
    "card_number": "YSD-EN032",
    "language": "en",
    "pack_id": "13304000",
    "rarity_id": 1
  },
  {
    "card_count": 1,
    "card_id": 4850,
    "card_image_id": 1,
    "card_number": "YSD-EN033",
    "language": "en",
    "pack_id": "13304000",
    "rarity_id": 1
  },
  {
    "card_count": 1,
    "card_id": 4856,
    "card_image_id": 1,
    "card_number": "YSD-EN026",
    "language": "en",
    "pack_id": "13304000",
    "rarity_id": 1
  },
  {
    "card_count": 1,
    "card_id": 4891,
    "card_image_id": 1,
    "card_number": "YSD-EN027",
    "language": "en",
    "pack_id": "13304000",
    "rarity_id": 1
  },
  {
    "card_count": 1,
    "card_id": 4932,
    "card_image_id": 1,
    "card_number": "YSD-EN022",
    "language": "en",
    "pack_id": "13304000",
    "rarity_id": 1
  },
  {
    "card_count": 1,
    "card_id": 4966,
    "card_image_id": 1,
    "card_number": "YSD-EN023",
    "language": "en",
    "pack_id": "13304000",
    "rarity_id": 1
  },
  {
    "card_count": 1,
    "card_id": 4988,
    "card_image_id": 1,
    "card_number": "YSD-EN035",
    "language": "en",
    "pack_id": "13304000",
    "rarity_id": 1
  },
  {
    "card_count": 1,
    "card_id": 5124,
    "card_image_id": 1,
    "card_number": "YSD-EN040",
    "language": "en",
    "pack_id": "13304000",
    "rarity_id": 1
  },
  {
    "card_count": 1,
    "card_id": 5210,
    "card_image_id": 1,
    "card_number": "YSD-EN036",
    "language": "en",
    "pack_id": "13304000",
    "rarity_id": 1
  },
  {
    "card_count": 1,
    "card_id": 5320,
    "card_image_id": 1,
    "card_number": "YSD-EN002",
    "language": "en",
    "pack_id": "13304000",
    "rarity_id": 1
  },
  {
    "card_count": 1,
    "card_id": 5330,
    "card_image_id": 1,
    "card_number": "YSD-EN028",
    "language": "en",
    "pack_id": "13304000",
    "rarity_id": 1
  },
  {
    "card_count": 1,
    "card_id": 5331,
    "card_image_id": 1,
    "card_number": "YSD-EN034",
    "language": "en",
    "pack_id": "13304000",
    "rarity_id": 1
  },
  {
    "card_count": 1,
    "card_id": 5334,
    "card_image_id": 1,
    "card_number": "YSD-EN015",
    "language": "en",
    "pack_id": "13304000",
    "rarity_id": 1
  },
  {
    "card_count": 1,
    "card_id": 5349,
    "card_image_id": 1,
    "card_number": "YSD-EN003",
    "language": "en",
    "pack_id": "13304000",
    "rarity_id": 1
  },
  {
    "card_count": 1,
    "card_id": 5581,
    "card_image_id": 1,
    "card_number": "YSD-EN004",
    "language": "en",
    "pack_id": "13304000",
    "rarity_id": 1
  },
  {
    "card_count": 1,
    "card_id": 5644,
    "card_image_id": 1,
    "card_number": "YSD-EN005",
    "language": "en",
    "pack_id": "13304000",
    "rarity_id": 1
  },
  {
    "card_count": 1,
    "card_id": 5799,
    "card_image_id": 1,
    "card_number": "YSD-EN037",
    "language": "en",
    "pack_id": "13304000",
    "rarity_id": 1
  },
  {
    "card_count": 1,
    "card_id": 5914,
    "card_image_id": 1,
    "card_number": "YSD-EN038",
    "language": "en",
    "pack_id": "13304000",
    "rarity_id": 1
  },
  {
    "card_count": 1,
    "card_id": 5947,
    "card_image_id": 1,
    "card_number": "YSD-EN006",
    "language": "en",
    "pack_id": "13304000",
    "rarity_id": 1
  },
  {
    "card_count": 1,
    "card_id": 6037,
    "card_image_id": 1,
    "card_number": "YSD-EN016",
    "language": "en",
    "pack_id": "13304000",
    "rarity_id": 1
  },
  {
    "card_count": 1,
    "card_id": 6121,
    "card_image_id": 1,
    "card_number": "YSD-EN017",
    "language": "en",
    "pack_id": "13304000",
    "rarity_id": 1
  },
  {
    "card_count": 1,
    "card_id": 6129,
    "card_image_id": 1,
    "card_number": "YSD-EN029",
    "language": "en",
    "pack_id": "13304000",
    "rarity_id": 1
  },
  {
    "card_count": 1,
    "card_id": 6148,
    "card_image_id": 1,
    "card_number": "YSD-EN039",
    "language": "en",
    "pack_id": "13304000",
    "rarity_id": 1
  },
  {
    "card_count": 1,
    "card_id": 6196,
    "card_image_id": 1,
    "card_number": "YSD-EN018",
    "language": "en",
    "pack_id": "13304000",
    "rarity_id": 1
  },
  {
    "card_count": 1,
    "card_id": 6213,
    "card_image_id": 1,
    "card_number": "YSD-EN030",
    "language": "en",
    "pack_id": "13304000",
    "rarity_id": 1
  },
  {
    "card_count": 1,
    "card_id": 6310,
    "card_image_id": 1,
    "card_number": "YSD-EN007",
    "language": "en",
    "pack_id": "13304000",
    "rarity_id": 1
  },
  {
    "card_count": 1,
    "card_id": 6311,
    "card_image_id": 1,
    "card_number": "YSD-EN008",
    "language": "en",
    "pack_id": "13304000",
    "rarity_id": 1
  },
  {
    "card_count": 1,
    "card_id": 6312,
    "card_image_id": 1,
    "card_number": "YSD-EN009",
    "language": "en",
    "pack_id": "13304000",
    "rarity_id": 1
  },
  {
    "card_count": 1,
    "card_id": 6313,
    "card_image_id": 1,
    "card_number": "YSD-EN010",
    "language": "en",
    "pack_id": "13304000",
    "rarity_id": 1
  },
  {
    "card_count": 1,
    "card_id": 6477,
    "card_image_id": 1,
    "card_number": "YSD-EN019",
    "language": "en",
    "pack_id": "13304000",
    "rarity_id": 4
  }
]