[
  {
    "card_count": 1,
    "card_id": 4371,
    "card_image_id": 1,
    "card_number": "PRC1-FR003",
    "language": "fr",
    "pack_id": "35509000",
    "rarity_id": 3
  },
  {
    "card_count": 1,
    "card_id": 4680,
    "card_image_id": 1,
    "card_number": "PRC1-FR002",
    "language": "fr",
    "pack_id": "35509000",
    "rarity_id": 3
  },
  {
    "card_count": 1,
    "card_id": 4718,
    "card_image_id": 1,
    "card_number": "PRC1-FR001",
    "language": "fr",
    "pack_id": "35509000",
    "rarity_id": 3
  },
  {
    "card_count": 1,
    "card_id": 4719,
    "card_image_id": 1,
    "card_number": "PRC1-FR004",
    "language": "fr",
    "pack_id": "35509000",
    "rarity_id": 3
  },
  {
    "card_count": 1,
    "card_id": 4720,
    "card_image_id": 1,
    "card_number": "PRC1-FR005",
    "language": "fr",
    "pack_id": "35509000",
    "rarity_id": 3
  },
  {
    "card_count": 1,
    "card_id": 8545,
    "card_image_id": 1,
    "card_number": "PRC1-FRV01",
    "language": "fr",
    "pack_id": "35509000",
    "rarity_id": 5
  },
  {
    "card_count": 1,
    "card_id": 8742,
    "card_image_id": 1,
    "card_number": "PRC1-FR007",
    "language": "fr",
    "pack_id": "35509000",
    "rarity_id": 3
  },
  {
    "card_count": 1,
    "card_id": 8745,
    "card_image_id": 1,
    "card_number": "PRC1-FR008",
    "language": "fr",
    "pack_id": "35509000",
    "rarity_id": 3
  },
  {
    "card_count": 1,
    "card_id": 8746,
    "card_image_id": 1,
    "card_number": "PRC1-FR006",
    "language": "fr",
    "pack_id": "35509000",
    "rarity_id": 3
  },
  {
    "card_count": 1,
    "card_id": 9013,
    "card_image_id": 1,
    "card_number": "PRC1-FR009",
    "language": "fr",
    "pack_id": "35509000",
    "rarity_id": 3
  },
  {
    "card_count": 1,
    "card_id": 9016,
    "card_image_id": 1,
    "card_number": "PRC1-FR013",
    "language": "fr",
    "pack_id": "35509000",
    "rarity_id": 3
  },
  {
    "card_count": 1,
    "card_id": 9256,
    "card_image_id": 1,
    "card_number": "PRC1-FR012",
    "language": "fr",
    "pack_id": "35509000",
    "rarity_id": 3
  },
  {
    "card_count": 1,
    "card_id": 9272,
    "card_image_id": 1,
    "card_number": "PRC1-FR018",
    "language": "fr",
    "pack_id": "35509000",
    "rarity_id": 5
  },
  {
    "card_count": 1,
    "card_id": 9420,
    "card_image_id": 1,
    "card_number": "PRC1-FR010",
    "language": "fr",
    "pack_id": "35509000",
    "rarity_id": 3
  },
  {
    "card_count": 1,
    "card_id": 9434,
    "card_image_id": 1,
    "card_number": "PRC1-FR011",
    "language": "fr",
    "pack_id": "35509000",
    "rarity_id": 3
  },
  {
    "card_count": 1,
    "card_id": 9559,
    "card_image_id": 1,
    "card_number": "PRC1-FR019",
    "language": "fr",
    "pack_id": "35509000",
    "rarity_id": 5
  },
  {
    "card_count": 1,
    "card_id": 9658,
    "card_image_id": 2,
    "card_number": "PRC1-FRV02",
    "language": "fr",
    "pack_id": "35509000",
    "rarity_id": 5
  },
  {
    "card_count": 1,
    "card_id": 9965,
    "card_image_id": 1,
    "card_number": "PRC1-FR014",
    "language": "fr",
    "pack_id": "35509000",
    "rarity_id": 5
  },
  {
    "card_count": 1,
    "card_id": 9966,
    "card_image_id": 1,
    "card_number": "PRC1-FR015",
    "language": "fr",
    "pack_id": "35509000",
    "rarity_id": 5
  },
  {
    "card_count": 1,
    "card_id": 9967,
    "card_image_id": 1,
    "card_number": "PRC1-FR016",
    "language": "fr",
    "pack_id": "35509000",
    "rarity_id": 5
  },
  {
    "card_count": 1,
    "card_id": 9968,
    "card_image_id": 1,
    "card_number": "PRC1-FR017",
    "language": "fr",
    "pack_id": "35509000",
    "rarity_id": 5
  },
  {
    "card_count": 1,
    "card_id": 9969,
    "card_image_id": 1,
    "card_number": "PRC1-FR020",
    "language": "fr",
    "pack_id": "35509000",
    "rarity_id": 5
  },
  {
    "card_count": 1,
    "card_id": 9970,
    "card_image_id": 1,
    "card_number": "PRC1-FR021",
    "language": "fr",
    "pack_id": "35509000",
    "rarity_id": 5
  },
  {
    "card_count": 1,
    "card_id": 9971,
    "card_image_id": 1,
    "card_number": "PRC1-FR022",
    "language": "fr",
    "pack_id": "35509000",
    "rarity_id": 5
  },
  {
    "card_count": 1,
    "card_id": 9972,
    "card_image_id": 1,
    "card_number": "PRC1-FR023",
    "language": "fr",
    "pack_id": "35509000",
    "rarity_id": 3
  }
]