{
  "attack_power": "1800",
  "attribute_id": 4,
  "card_id": 5641,
  "card_name": "그레이트 앵거스",
  "card_name_label": "",
  "card_name_search": "",
  "card_pen_effect": "",
  "card_text": "미친듯이 난폭하게 구는 야수. 온순한 모습을 본 사람이 없다할 정도로 상당히 흉폭하다.",
  "defense_power": "600",
  "effect_id": 0,
  "language": "ko",
  "legend_type": "",
  "linkmarker": "",
  "linkno": "",
  "min_card_image_id": 1,
  "note": "",
  "other_item_id": 0,
  "pen_scale_l": "",
  "pen_scale_r": "",
  "sales_at": "2004/11/26",
  "species_id": 11,
  "starchip": "4"
}