{
  "attack_power": "2200",
  "attribute_id": 3,
  "card_id": 12842,
  "card_name": "デストーイ・ハーケン・クラーケン",
  "card_name_label": "デストーイ・ハーケン・クラーケン",
  "card_name_search": "ですとーいはーけんくらーけん",
  "card_pen_effect": "",
  "card_text": "「エッジインプ」モンスター＋「ファーニマル」モンスター$N①：１ターンに１度、相手フィールドのモンスター１体を対象として発動できる。そのモンスターを墓地へ送る。この効果を発動するターン、このカードは直接攻撃できない。②：このカードは１度のバトルフェイズ中に２回攻撃できる。③：このカードが戦闘を行ったバトルフェイズ終了時に発動できる。このカードを守備表示にする。",
  "defense_power": "3000",
  "effect_id": 0,
  "language": "ja",
  "legend_type": "",
  "linkmarker": "",
  "linkno": "",
  "min_card_image_id": 1,
  "note": "",
  "other_item_id": 3,
  "pen_scale_l": "",
  "pen_scale_r": "",
  "sales_at": "2016/11/12",
  "species_id": 3,
  "starchip": "8"
}