{
  "attack_power": "2200",
  "attribute_id": 5,
  "card_id": 9502,
  "card_name": "カラクリ忍者 七七四九",
  "card_name_label": "カラクリにんじゃ　ナナシック",
  "card_name_search": "からくりにんじゃななしっく",
  "card_pen_effect": "",
  "card_text": "このカードは攻撃可能な場合には攻撃しなければならない。フィールド上に表側表示で存在するこのカードが攻撃対象に選択された時、このカードの表示形式を変更する。このカードが召喚に成功した時、自分フィールド上に表側守備表示で存在する「カラクリ」と名のついたモンスターの数だけ、自分のデッキからカードをドローする事ができる。",
  "defense_power": "1800",
  "effect_id": 0,
  "language": "ja",
  "legend_type": "",
  "linkmarker": "",
  "linkno": "",
  "note": "",
  "other_item_id": 1,
  "pen_scale_l": "",
  "pen_scale_r": "",
  "sales_at": "2011/02/11",
  "species_id": 7,
  "starchip": "5"
}