{
  "attack_power": "0",
  "attribute_id": 9,
  "card_id": 10427,
  "card_name": "Dimension Gate",
  "card_name_label": "",
  "card_name_search": "",
  "card_pen_effect": "",
  "card_text": "Activate this card by targeting 1 monster you control; banish that target face-up. When an opponent's monster declares a direct attack: You can send this face-up card on the field to the Graveyard. If this card is sent to the Graveyard: You can Special Summon the monster banished by this card's effect.",
  "defense_power": "0",
  "effect_id": 4,
  "language": "en",
  "legend_type": "",
  "linkmarker": "",
  "linkno": "",
  "note": "",
  "other_item_id": 14,
  "pen_scale_l": "",
  "pen_scale_r": "",
  "sales_at": "2013/01/25",
  "species_id": 25,
  "starchip": "0"
}