{
  "attack_power": "1800",
  "attribute_id": 5,
  "card_id": 10980,
  "card_name": "Dododo Driver",
  "card_name_label": "",
  "card_name_search": "",
  "card_pen_effect": "",
  "card_text": "Up to twice per turn, if this card was Special Summoned by the effect of a \"Dododo\" monster this turn: You can target 1 \"Dododo\" monster you control, then activate 1 of these effects;$N●Increase its Level by 1.$N●Reduce its Level by 1.",
  "defense_power": "200",
  "effect_id": 0,
  "language": "en",
  "legend_type": "",
  "linkmarker": "",
  "linkno": "",
  "note": "",
  "other_item_id": 1,
  "pen_scale_l": "",
  "pen_scale_r": "",
  "sales_at": "2014/11/07",
  "species_id": 15,
  "starchip": "4"
}