{
  "attack_power": "0",
  "attribute_id": 1,
  "card_id": 17230,
  "card_name": "The Great Double Casted Caster",
  "card_name_label": "",
  "card_name_search": "",
  "card_pen_effect": "",
  "card_text": "2 non-Effect Monsters$NGains ATK equal to the combined original ATK of any Ritual, Fusion, Synchro, Xyz, or Link Monsters used as Fusion Material for this card. This card can attack directly. If this card is destroyed by battle or card effect: You can target 1 of your non-Effect Monsters that is banished or in your GY; Special Summon it. You can only use this effect of \"The Great Double Casted Caster\" once per turn.",
  "defense_power": "2600",
  "effect_id": 0,
  "language": "en",
  "legend_type": "",
  "linkmarker": "",
  "linkno": "",
  "note": "",
  "other_item_id": 3,
  "pen_scale_l": "",
  "pen_scale_r": "",
  "sales_at": "2022/02/10",
  "species_id": 18,
  "starchip": "8"
}