{
  "attack_power": "0",
  "attribute_id": 9,
  "card_id": 17478,
  "card_name": "Exosister Returnia",
  "card_name_label": "",
  "card_name_search": "",
  "card_pen_effect": "",
  "card_text": "If all monsters you control are \"Exosister\" monsters (min. 1): Pay 800 LP, then target 1 card your opponent controls or in their GY; banish it, then you can apply 1 of the following effects.$N●Immediately after this effect resolves, Xyz Summon 1 \"Exosister\" Xyz Monster using monsters you control.$N●If you Xyz Summoned this turn, banish 1 card your opponent controls.$NYou can only activate 1 \"Exosister Returnia\" per turn.",
  "defense_power": "0",
  "effect_id": 0,
  "language": "en",
  "legend_type": "",
  "linkmarker": "",
  "linkno": "",
  "min_card_image_id": 1,
  "note": "",
  "other_item_id": 14,
  "pen_scale_l": "",
  "pen_scale_r": "",
  "sales_at": "2022/08/04",
  "species_id": 25,
  "starchip": "0"
}