{
  "attack_power": "1500",
  "attribute_id": 3,
  "card_id": 13669,
  "card_name": "Força Celeste - Ás - Shizuku",
  "card_name_label": "",
  "card_name_search": "",
  "card_pen_effect": "",
  "card_text": "1 monstro \"Força Celeste - Ás\" que não seja de ÁGUA$NMonstros que seu oponente controla perdem 100 de ATK/DEF para cada Magia no seu Cemitério. Uma vez por turno, durante a Fase Final, se este card foi Invocado por Invocação-Especial neste turno: você pode adicionar 1 Magia \"Força Celeste\" com um nome diferente que o dos cards no seu Cemitério, do seu Deck à sua mão. Você só pode Invocar um ou mais \"Força Celeste - Ás - Shizuku\" por Invocação-Especial uma vez por turno.",
  "defense_power": "",
  "effect_id": 0,
  "language": "pt",
  "legend_type": "",
  "linkmarker": "9",
  "linkno": "1",
  "note": "",
  "other_item_id": 43,
  "pen_scale_l": "",
  "pen_scale_r": "",
  "sales_at": "2018/05/24",
  "species_id": 7,
  "starchip": ""
}