{
  "attack_power": "3000",
  "attribute_id": 2,
  "card_id": 13836,
  "card_name": "Dragão Gumblar Topológico",
  "card_name_label": "",
  "card_name_search": "",
  "card_pen_effect": "",
  "card_text": "2+ Monstros de Efeito$NSe outro monstro for Invocado por Invocação-Especial em uma zona para a qual um Monstro Link apontar, enquanto este monstro estiver no campo: descarte 1 ou 2 cards aleatórios e, depois, seu oponente descarta o mesmo número. Durante sua Fase Principal, se este card estiver Extra Linkado e seu oponente tiver pelo menos 1 card na mão dele: você pode fazer com que seu oponente descarte 1 ou 2 cards (o que for maior) e, depois, se ele não tiver mais cards na mão dele, cause 3000 de dano a ele. Você só pode usar 1 efeito de \"Dragão Gumblar Topológico\" por turno e apenas uma vez por turno.",
  "defense_power": "",
  "effect_id": 0,
  "language": "pt",
  "legend_type": "",
  "linkmarker": "8462",
  "linkno": "4",
  "note": "",
  "other_item_id": 43,
  "pen_scale_l": "",
  "pen_scale_r": "",
  "sales_at": "2018/06/28",
  "species_id": 27,
  "starchip": ""
}