{
  "attack_power": "2200",
  "attribute_id": 5,
  "card_id": 14127,
  "card_name": "T.G. Lançador de Tridente",
  "card_name_label": "",
  "card_name_search": "",
  "card_pen_effect": "",
  "card_text": "2+ Monstros de Efeito, incluindo um Regulador \"T.G.\"$NSe este card for Invocado por Invocação-Link, você pode: Invocar por Invocação-Especial 3 monstros \"T.G.\" (1 da sua mão, 1 do seu Deck e 1 do seu Cemitério) em Posição de Defesa em zonas suas para as quais este card apontar e, além disso, você não pode Invocar monstros por Invocação-Especial pelo resto deste turno, exceto monstros \"T.G.\". Você só pode usar este efeito de \"T.G. Lançador de Tridente\" uma vez por turno. Seu oponente não pode escolher Monstros Sincro \"T.G.\" para os quais este card apontar como alvo de efeitos de card.",
  "defense_power": "",
  "effect_id": 0,
  "language": "pt",
  "legend_type": "",
  "linkmarker": "123",
  "linkno": "3",
  "note": "",
  "other_item_id": 43,
  "pen_scale_l": "",
  "pen_scale_r": "",
  "sales_at": "2019/01/31",
  "species_id": 7,
  "starchip": ""
}