{
  "attack_power": "400",
  "attribute_id": 4,
  "card_id": 14238,
  "card_name": "Salamagrande Guaxinim",
  "card_name_label": "",
  "card_name_search": "",
  "card_pen_effect": "",
  "card_text": "Quando um monstro \"Salamagrande\" seu for escolhido como alvo de um ataque por um monstro do oponente: você pode enviar este card da sua mão para o Cemitério e, depois, escolher esses 2 monstros que iriam batalhar; ganhe PV igual ao ATK desse monstro do oponente e, além disso seu monstro alvo não pode ser destruído em batalha neste turno. Quando um monstro \"Salamagrande\" seu destruir um monstro do oponente em batalha e enviá-lo para o Cemitério, enquanto este card estiver no seu Cemitério: você pode adicionar este card à sua mão. Você só pode usar este efeito de \"Salamagrande Guaxinim\" uma vez por turno.",
  "defense_power": "800",
  "effect_id": 0,
  "language": "pt",
  "legend_type": "",
  "linkmarker": "",
  "linkno": "",
  "note": "",
  "other_item_id": 1,
  "pen_scale_l": "",
  "pen_scale_r": "",
  "sales_at": "2019/02/14",
  "species_id": 27,
  "starchip": "1"
}