{
  "attack_power": "2400",
  "attribute_id": 2,
  "card_id": 14369,
  "card_name": "Dragão Negro Alternativo de Olhos Vermelhos",
  "card_name_label": "",
  "card_name_search": "",
  "card_pen_effect": "",
  "card_text": "Não pode ser Invocado por Invocação-Normal/Baixado. Primeiro deve ser Invocado por Invocação-Especial (da sua mão) ao oferecer como Tributo 1 monstro \"Olhos Vermelhos\" da sua mão ou do campo. Você só pode Invocar \"Dragão Negro Alternativo de Olhos Vermelhos\" por Invocação-Especial uma vez por turno desta forma. Se este card for destruído em batalha ou se este card em posse do seu dono for destruído por um efeito de card do oponente: você pode escolher 1 monstro \"Olhos Vermelhos\" de Nível 7 ou menos no seu Cemitério, exceto \"Dragão Negro Alternativo de Olhos Vermelhos\"; Invoque-o por Invocação-Especial e se ele era um \"Dragão Negro de Olhos Vermelhos\" que tenha sido Invocado por Invocação-Especial, seu ATK original se torna o dobro.",
  "defense_power": "2000",
  "effect_id": 0,
  "language": "pt",
  "legend_type": "",
  "linkmarker": "",
  "linkno": "",
  "note": "",
  "other_item_id": 27,
  "pen_scale_l": "",
  "pen_scale_r": "",
  "sales_at": "2019/08/30",
  "species_id": 1,
  "starchip": "7"
}