{
  "attack_power": "0",
  "attribute_id": 8,
  "card_id": 14381,
  "card_name": "Dharma Cúbico",
  "card_name_label": "",
  "card_name_search": "",
  "card_pen_effect": "",
  "card_text": "Você não sofre dano de batalha dos ataques envolvendo seus monstros \"Cúbico(a)\". Você só pode usar cada um dos seguintes efeitos de \"Dharma Cúbico\" uma vez por turno, durante sua Fase Principal:$N●Você pode enviar 1 card \"Cúbico(a)\" da sua mão para o Cemitério e, se isso acontecer, compre 1 card.$N●Você pode banir este card do seu Cemitério e, depois, escolha 1 monstro \"Cúbico(a)\" no seu Cemitério; adicione-o à sua mão.",
  "defense_power": "0",
  "effect_id": 4,
  "language": "pt",
  "legend_type": "",
  "linkmarker": "",
  "linkno": "",
  "min_card_image_id": 1,
  "note": "",
  "other_item_id": 13,
  "pen_scale_l": "",
  "pen_scale_r": "",
  "sales_at": "2020/03/19",
  "species_id": 24,
  "starchip": "0"
}