{
  "attack_power": "1400",
  "attribute_id": 2,
  "card_id": 17760,
  "card_name": "Asanegra - Sudri, o Cintilar Fantasma",
  "card_name_label": "",
  "card_name_search": "",
  "card_pen_effect": "",
  "card_text": "Quando este card for Invocado por Invocação-Normal: você pode adicionar 1 card que mencione \"Dragão de Asas Negras\" do seu Deck à sua mão, exceto \"Asanegra - Sudri, o Cintilar Fantasma\". Você pode oferecer 1 monstro como Tributo; Invoque por Invocação-Especial 1 \"Ficha de Cintilar Fantasma\" (Besta Alada/Regulador/TREVAS/Nível 2/ATK 700/DEF 700) e, depois, você sofre 700 de dano. Você não pode Invocar monstros por Invocação-Especial do Deck Adicional no turno em que ativar este efeito, exceto Monstros Sincro. Você só pode usar este efeito de \"Asanegra - Sudri, o Cintilar Fantasma\" uma vez por turno.",
  "defense_power": "1400",
  "effect_id": 0,
  "language": "pt",
  "legend_type": "",
  "linkmarker": "",
  "linkno": "",
  "min_card_image_id": 1,
  "note": "",
  "other_item_id": 1,
  "pen_scale_l": "",
  "pen_scale_r": "",
  "sales_at": "2022/10/20",
  "species_id": 16,
  "starchip": "4"
}