{
  "attack_power": "500",
  "attribute_id": 4,
  "card_id": 19874,
  "card_name": "Brasas Esfriando",
  "card_name_label": "",
  "card_name_search": "",
  "card_pen_effect": "",
  "card_text": "Se um duelista ganhar PV (exceto durante a Etapa de Dano): você pode Invocar este card por Invocação-Especial da sua mão. Uma vez por turno, se um duelista ganhar PV enquanto este card estiver na Zona de Monstros (exceto durante a Etapa de Dano): você pode fazer com que 1 duelista ganhe 1000 PV.",
  "defense_power": "1500",
  "effect_id": 0,
  "language": "pt",
  "legend_type": "",
  "linkmarker": "",
  "linkno": "",
  "min_card_image_id": 1,
  "note": "",
  "other_item_id": 1,
  "pen_scale_l": "",
  "pen_scale_r": "",
  "sales_at": "2024/04/25",
  "species_id": 4,
  "starchip": "3"
}