[
  {
    "card_count": 1,
    "card_id": 11301,
    "card_image_id": 1,
    "card_number": "CORE-IT090",
    "language": "it",
    "pack_id": "41114006",
    "rarity_id": 1
  },
  {
    "card_count": 1,
    "card_id": 11307,
    "card_image_id": 1,
    "card_number": "CORE-IT091",
    "language": "it",
    "pack_id": "41114006",
    "rarity_id": 2
  },
  {
    "card_count": 1,
    "card_id": 11331,
    "card_image_id": 1,
    "card_number": "CORE-IT093",
    "language": "it",
    "pack_id": "41114006",
    "rarity_id": 1
  },
  {
    "card_count": 1,
    "card_id": 11453,
    "card_image_id": 1,
    "card_number": "CORE-IT092",
    "language": "it",
    "pack_id": "41114006",
    "rarity_id": 4
  },
  {
    "card_count": 1,
    "card_id": 11618,
    "card_image_id": 1,
    "card_number": "CORE-IT094",
    "language": "it",
    "pack_id": "41114006",
    "rarity_id": 3
  },
  {
    "card_count": 1,
    "card_id": 11640,
    "card_image_id": 1,
    "card_number": "CORE-IT095",
    "language": "it",
    "pack_id": "41114006",
    "rarity_id": 4
  },
  {
    "card_count": 1,
    "card_id": 11658,
    "card_image_id": 1,
    "card_number": "CORE-IT096",
    "language": "it",
    "pack_id": "41114006",
    "rarity_id": 2
  },
  {
    "card_count": 1,
    "card_id": 11659,
    "card_image_id": 1,
    "card_number": "CORE-IT097",
    "language": "it",
    "pack_id": "41114006",
    "rarity_id": 2
  },
  {
    "card_count": 1,
    "card_id": 11660,
    "card_image_id": 1,
    "card_number": "CORE-IT098",
    "language": "it",
    "pack_id": "41114006",
    "rarity_id": 5
  },
  {
    "card_count": 1,
    "card_id": 11662,
    "card_image_id": 1,
    "card_number": "CORE-IT099",
    "language": "it",
    "pack_id": "41114006",
    "rarity_id": 1
  },
  {
    "card_count": 1,
    "card_id": 11785,
    "card_image_id": 1,
    "card_number": "CORE-IT001",
    "language": "it",
    "pack_id": "41114006",
    "rarity_id": 1
  },
  {
    "card_count": 1,
    "card_id": 11786,
    "card_image_id": 1,
    "card_number": "CORE-IT002",
    "language": "it",
    "pack_id": "41114006",
    "rarity_id": 1
  },
  {
    "card_count": 1,
    "card_id": 11787,
    "card_image_id": 1,
    "card_number": "CORE-IT003",
    "language": "it",
    "pack_id": "41114006",
    "rarity_id": 3
  },
  {
    "card_count": 1,
    "card_id": 11788,
    "card_image_id": 1,
    "card_number": "CORE-IT004",
    "language": "it",
    "pack_id": "41114006",
    "rarity_id": 3
  },
  {
    "card_count": 1,
    "card_id": 11789,
    "card_image_id": 1,
    "card_number": "CORE-IT005",
    "language": "it",
    "pack_id": "41114006",
    "rarity_id": 1
  },
  {
    "card_count": 1,
    "card_id": 11790,
    "card_image_id": 1,
    "card_number": "CORE-IT006",
    "language": "it",
    "pack_id": "41114006",
    "rarity_id": 1
  },
  {
    "card_count": 1,
    "card_id": 11791,
    "card_image_id": 1,
    "card_number": "CORE-IT007",
    "language": "it",
    "pack_id": "41114006",
    "rarity_id": 1
  },
  {
    "card_count": 1,
    "card_id": 11792,
    "card_image_id": 1,
    "card_number": "CORE-IT008",
    "language": "it",
    "pack_id": "41114006",
    "rarity_id": 1
  },
  {
    "card_count": 1,
    "card_id": 11793,
    "card_image_id": 1,
    "card_number": "CORE-IT009",
    "language": "it",
    "pack_id": "41114006",
    "rarity_id": 1
  },
  {
    "card_count": 1,
    "card_id": 11794,
    "card_image_id": 1,
    "card_number": "CORE-IT010",
    "language": "it",
    "pack_id": "41114006",
    "rarity_id": 3
  },
  {
    "card_count": 1,
    "card_id": 11795,
    "card_image_id": 1,
    "card_number": "CORE-IT011",
    "language": "it",
    "pack_id": "41114006",
    "rarity_id": 1
  },
  {
    "card_count": 1,
    "card_id": 11796,
    "card_image_id": 1,
    "card_number": "CORE-IT012",
    "language": "it",
    "pack_id": "41114006",
    "rarity_id": 2
  },
  {
    "card_count": 1,
    "card_id": 11797,
    "card_image_id": 1,
    "card_number": "CORE-IT013",
    "language": "it",
    "pack_id": "41114006",
    "rarity_id": 1
  },
  {
    "card_count": 1,
    "card_id": 11798,
    "card_image_id": 1,
    "card_number": "CORE-IT014",
    "language": "it",
    "pack_id": "41114006",
    "rarity_id": 1
  },
  {
    "card_count": 1,
    "card_id": 11799,
    "card_image_id": 1,
    "card_number": "CORE-IT015",
    "language": "it",
    "pack_id": "41114006",
    "rarity_id": 1
  },
  {
    "card_count": 1,
    "card_id": 11800,
    "card_image_id": 1,
    "card_number": "CORE-IT016",
    "language": "it",
    "pack_id": "41114006",
    "rarity_id": 1
  },
  {
    "card_count": 1,
    "card_id": 11801,
    "card_image_id": 1,
    "card_number": "CORE-IT017",
    "language": "it",
    "pack_id": "41114006",
    "rarity_id": 1
  },
  {
    "card_count": 1,
    "card_id": 11802,
    "card_image_id": 1,
    "card_number": "CORE-IT018",
    "language": "it",
    "pack_id": "41114006",
    "rarity_id": 1
  },
  {
    "card_count": 1,
    "card_id": 11803,
    "card_image_id": 1,
    "card_number": "CORE-IT019",
    "language": "it",
    "pack_id": "41114006",
    "rarity_id": 1
  },
  {
    "card_count": 1,
    "card_id": 11804,
    "card_image_id": 1,
    "card_number": "CORE-IT020",
    "language": "it",
    "pack_id": "41114006",
    "rarity_id": 3
  },
  {
    "card_count": 1,
    "card_id": 11805,
    "card_image_id": 1,
    "card_number": "CORE-IT021",
    "language": "it",
    "pack_id": "41114006",
    "rarity_id": 5
  },
  {
    "card_count": 1,
    "card_id": 11806,
    "card_image_id": 1,
    "card_number": "CORE-IT022",
    "language": "it",
    "pack_id": "41114006",
    "rarity_id": 1
  },
  {
    "card_count": 1,
    "card_id": 11807,
    "card_image_id": 1,
    "card_number": "CORE-IT023",
    "language": "it",
    "pack_id": "41114006",
    "rarity_id": 3
  },
  {
    "card_count": 1,
    "card_id": 11808,
    "card_image_id": 1,
    "card_number": "CORE-IT024",
    "language": "it",
    "pack_id": "41114006",
    "rarity_id": 1
  },
  {
    "card_count": 1,
    "card_id": 11809,
    "card_image_id": 1,
    "card_number": "CORE-IT025",
    "language": "it",
    "pack_id": "41114006",
    "rarity_id": 3
  },
  {
    "card_count": 1,
    "card_id": 11810,
    "card_image_id": 1,
    "card_number": "CORE-IT026",
    "language": "it",
    "pack_id": "41114006",
    "rarity_id": 1
  },
  {
    "card_count": 1,
    "card_id": 11811,
    "card_image_id": 1,
    "card_number": "CORE-IT027",
    "language": "it",
    "pack_id": "41114006",
    "rarity_id": 3
  },
  {
    "card_count": 1,
    "card_id": 11812,
    "card_image_id": 1,
    "card_number": "CORE-IT028",
    "language": "it",
    "pack_id": "41114006",
    "rarity_id": 4
  },
  {
    "card_count": 1,
    "card_id": 11813,
    "card_image_id": 1,
    "card_number": "CORE-IT029",
    "language": "it",
    "pack_id": "41114006",
    "rarity_id": 1
  },
  {
    "card_count": 1,
    "card_id": 11814,
    "card_image_id": 1,
    "card_number": "CORE-IT030",
    "language": "it",
    "pack_id": "41114006",
    "rarity_id": 1
  },
  {
    "card_count": 1,
    "card_id": 11815,
    "card_image_id": 1,
    "card_number": "CORE-IT031",
    "language": "it",
    "pack_id": "41114006",
    "rarity_id": 1
  },
  {
    "card_count": 1,
    "card_id": 11816,
    "card_image_id": 1,
    "card_number": "CORE-IT032",
    "language": "it",
    "pack_id": "41114006",
    "rarity_id": 2
  },
  {
    "card_count": 1,
    "card_id": 11817,
    "card_image_id": 1,
    "card_number": "CORE-IT033",
    "language": "it",
    "pack_id": "41114006",
    "rarity_id": 2
  },
  {
    "card_count": 1,
    "card_id": 11818,
    "card_image_id": 1,
    "card_number": "CORE-IT034",
    "language": "it",
    "pack_id": "41114006",
    "rarity_id": 5
  },
  {
    "card_count": 1,
    "card_id": 11819,
    "card_image_id": 1,
    "card_number": "CORE-IT035",
    "language": "it",
    "pack_id": "41114006",
    "rarity_id": 1
  },
  {
    "card_count": 1,
    "card_id": 11820,
    "card_image_id": 1,
    "card_number": "CORE-IT036",
    "language": "it",
    "pack_id": "41114006",
    "rarity_id": 4
  },
  {
    "card_count": 1,
    "card_id": 11821,
    "card_image_id": 1,
    "card_number": "CORE-IT037",
    "language": "it",
    "pack_id": "41114006",
    "rarity_id": 2
  },
  {
    "card_count": 1,
    "card_id": 11822,
    "card_image_id": 1,
    "card_number": "CORE-IT038",
    "language": "it",
    "pack_id": "41114006",
    "rarity_id": 1
  },
  {
    "card_count": 1,
    "card_id": 11823,
    "card_image_id": 1,
    "card_number": "CORE-IT039",
    "language": "it",
    "pack_id": "41114006",
    "rarity_id": 3
  },
  {
    "card_count": 1,
    "card_id": 11824,
    "card_image_id": 1,
    "card_number": "CORE-IT040",
    "language": "it",
    "pack_id": "41114006",
    "rarity_id": 1
  },
  {
    "card_count": 1,
    "card_id": 11825,
    "card_image_id": 1,
    "card_number": "CORE-IT041",
    "language": "it",
    "pack_id": "41114006",
    "rarity_id": 2
  },
  {
    "card_count": 1,
    "card_id": 11826,
    "card_image_id": 1,
    "card_number": "CORE-IT042",
    "language": "it",
    "pack_id": "41114006",
    "rarity_id": 5
  },
  {
    "card_count": 1,
    "card_id": 11827,
    "card_image_id": 1,
    "card_number": "CORE-IT043",
    "language": "it",
    "pack_id": "41114006",
    "rarity_id": 2
  },
  {
    "card_count": 1,
    "card_id": 11828,
    "card_image_id": 1,
    "card_number": "CORE-IT044",
    "language": "it",
    "pack_id": "41114006",
    "rarity_id": 1
  },
  {
    "card_count": 1,
    "card_id": 11829,
    "card_image_id": 1,
    "card_number": "CORE-IT045",
    "language": "it",
    "pack_id": "41114006",
    "rarity_id": 1
  },
  {
    "card_count": 1,
    "card_id": 11830,
    "card_image_id": 1,
    "card_number": "CORE-IT046",
    "language": "it",
    "pack_id": "41114006",
    "rarity_id": 2
  },
  {
    "card_count": 1,
    "card_id": 11831,
    "card_image_id": 1,
    "card_number": "CORE-IT047",
    "language": "it",
    "pack_id": "41114006",
    "rarity_id": 4
  },
  {
    "card_count": 1,
    "card_id": 11832,
    "card_image_id": 1,
    "card_number": "CORE-IT048",
    "language": "it",
    "pack_id": "41114006",
    "rarity_id": 4
  },
  {
    "card_count": 1,
    "card_id": 11832,
    "card_image_id": 1,
    "card_number": "CORE-IT048",
    "language": "it",
    "pack_id": "41114006",
    "rarity_id": 6
  },
  {
    "card_count": 1,
    "card_id": 11833,
    "card_image_id": 1,
    "card_number": "CORE-IT049",
    "language": "it",
    "pack_id": "41114006",
    "rarity_id": 4
  },
  {
    "card_count": 1,
    "card_id": 11833,
    "card_image_id": 1,
    "card_number": "CORE-IT049",
    "language": "it",
    "pack_id": "41114006",
    "rarity_id": 6
  },
  {
    "card_count": 1,
    "card_id": 11834,
    "card_image_id": 1,
    "card_number": "CORE-IT050",
    "language": "it",
    "pack_id": "41114006",
    "rarity_id": 4
  },
  {
    "card_count": 1,
    "card_id": 11834,
    "card_image_id": 1,
    "card_number": "CORE-IT050",
    "language": "it",
    "pack_id": "41114006",
    "rarity_id": 6
  },
  {
    "card_count": 1,
    "card_id": 11835,
    "card_image_id": 1,
    "card_number": "CORE-IT051",
    "language": "it",
    "pack_id": "41114006",
    "rarity_id": 5
  },
  {
    "card_count": 1,
    "card_id": 11835,
    "card_image_id": 1,
    "card_number": "CORE-IT051",
    "language": "it",
    "pack_id": "41114006",
    "rarity_id": 6
  },
  {
    "card_count": 1,
    "card_id": 11836,
    "card_image_id": 1,
    "card_number": "CORE-IT052",
    "language": "it",
    "pack_id": "41114006",
    "rarity_id": 2
  },
  {
    "card_count": 1,
    "card_id": 11837,
    "card_image_id": 1,
    "card_number": "CORE-IT053",
    "language": "it",
    "pack_id": "41114006",
    "rarity_id": 2
  },
  {
    "card_count": 1,
    "card_id": 11838,
    "card_image_id": 1,
    "card_number": "CORE-IT054",
    "language": "it",
    "pack_id": "41114006",
    "rarity_id": 5
  },
  {
    "card_count": 1,
    "card_id": 11838,
    "card_image_id": 1,
    "card_number": "CORE-IT054",
    "language": "it",
    "pack_id": "41114006",
    "rarity_id": 6
  },
  {
    "card_count": 1,
    "card_id": 11838,
    "card_image_id": 1,
    "card_number": "CORE-IT054",
    "language": "it",
    "pack_id": "41114006",
    "rarity_id": 7
  },
  {
    "card_count": 1,
    "card_id": 11839,
    "card_image_id": 1,
    "card_number": "CORE-IT055",
    "language": "it",
    "pack_id": "41114006",
    "rarity_id": 1
  },
  {
    "card_count": 1,
    "card_id": 11840,
    "card_image_id": 1,
    "card_number": "CORE-IT056",
    "language": "it",
    "pack_id": "41114006",
    "rarity_id": 3
  },
  {
    "card_count": 1,
    "card_id": 11841,
    "card_image_id": 1,
    "card_number": "CORE-IT057",
    "language": "it",
    "pack_id": "41114006",
    "rarity_id": 1
  },
  {
    "card_count": 1,
    "card_id": 11842,
    "card_image_id": 1,
    "card_number": "CORE-IT058",
    "language": "it",
    "pack_id": "41114006",
    "rarity_id": 1
  },
  {
    "card_count": 1,
    "card_id": 11843,
    "card_image_id": 1,
    "card_number": "CORE-IT059",
    "language": "it",
    "pack_id": "41114006",
    "rarity_id": 3
  },
  {
    "card_count": 1,
    "card_id": 11844,
    "card_image_id": 1,
    "card_number": "CORE-IT060",
    "language": "it",
    "pack_id": "41114006",
    "rarity_id": 4
  },
  {
    "card_count": 1,
    "card_id": 11845,
    "card_image_id": 1,
    "card_number": "CORE-IT061",
    "language": "it",
    "pack_id": "41114006",
    "rarity_id": 1
  },
  {
    "card_count": 1,
    "card_id": 11846,
    "card_image_id": 1,
    "card_number": "CORE-IT062",
    "language": "it",
    "pack_id": "41114006",
    "rarity_id": 1
  },
  {
    "card_count": 1,
    "card_id": 11847,
    "card_image_id": 1,
    "card_number": "CORE-IT063",
    "language": "it",
    "pack_id": "41114006",
    "rarity_id": 3
  },
  {
    "card_count": 1,
    "card_id": 11848,
    "card_image_id": 1,
    "card_number": "CORE-IT064",
    "language": "it",
    "pack_id": "41114006",
    "rarity_id": 1
  },
  {
    "card_count": 1,
    "card_id": 11849,
    "card_image_id": 1,
    "card_number": "CORE-IT065",
    "language": "it",
    "pack_id": "41114006",
    "rarity_id": 5
  },
  {
    "card_count": 1,
    "card_id": 11850,
    "card_image_id": 1,
    "card_number": "CORE-IT066",
    "language": "it",
    "pack_id": "41114006",
    "rarity_id": 1
  },
  {
    "card_count": 1,
    "card_id": 11851,
    "card_image_id": 1,
    "card_number": "CORE-IT067",
    "language": "it",
    "pack_id": "41114006",
    "rarity_id": 1
  },
  {
    "card_count": 1,
    "card_id": 11852,
    "card_image_id": 1,
    "card_number": "CORE-IT068",
    "language": "it",
    "pack_id": "41114006",
    "rarity_id": 1
  },
  {
    "card_count": 1,
    "card_id": 11853,
    "card_image_id": 1,
    "card_number": "CORE-IT069",
    "language": "it",
    "pack_id": "41114006",
    "rarity_id": 1
  },
  {
    "card_count": 1,
    "card_id": 11854,
    "card_image_id": 1,
    "card_number": "CORE-IT070",
    "language": "it",
    "pack_id": "41114006",
    "rarity_id": 1
  },
  {
    "card_count": 1,
    "card_id": 11855,
    "card_image_id": 1,
    "card_number": "CORE-IT071",
    "language": "it",
    "pack_id": "41114006",
    "rarity_id": 1
  },
  {
    "card_count": 1,
    "card_id": 11856,
    "card_image_id": 1,
    "card_number": "CORE-IT072",
    "language": "it",
    "pack_id": "41114006",
    "rarity_id": 1
  },
  {
    "card_count": 1,
    "card_id": 11857,
    "card_image_id": 1,
    "card_number": "CORE-IT073",
    "language": "it",
    "pack_id": "41114006",
    "rarity_id": 2
  },
  {
    "card_count": 1,
    "card_id": 11858,
    "card_image_id": 1,
    "card_number": "CORE-IT074",
    "language": "it",
    "pack_id": "41114006",
    "rarity_id": 1
  },
  {
    "card_count": 1,
    "card_id": 11859,
    "card_image_id": 1,
    "card_number": "CORE-IT075",
    "language": "it",
    "pack_id": "41114006",
    "rarity_id": 3
  },
  {
    "card_count": 1,
    "card_id": 11860,
    "card_image_id": 1,
    "card_number": "CORE-IT076",
    "language": "it",
    "pack_id": "41114006",
    "rarity_id": 5
  },
  {
    "card_count": 1,
    "card_id": 11861,
    "card_image_id": 1,
    "card_number": "CORE-IT077",
    "language": "it",
    "pack_id": "41114006",
    "rarity_id": 1
  },
  {
    "card_count": 1,
    "card_id": 11862,
    "card_image_id": 1,
    "card_number": "CORE-IT078",
    "language": "it",
    "pack_id": "41114006",
    "rarity_id": 1
  },
  {
    "card_count": 1,
    "card_id": 11863,
    "card_image_id": 1,
    "card_number": "CORE-IT079",
    "language": "it",
    "pack_id": "41114006",
    "rarity_id": 2
  },
  {
    "card_count": 1,
    "card_id": 11864,
    "card_image_id": 1,
    "card_number": "CORE-IT080",
    "language": "it",
    "pack_id": "41114006",
    "rarity_id": 1
  },
  {
    "card_count": 1,
    "card_id": 12031,
    "card_image_id": 1,
    "card_number": "CORE-IT000",
    "language": "it",
    "pack_id": "41114006",
    "rarity_id": 2
  },
  {
    "card_count": 1,
    "card_id": 12032,
    "card_image_id": 1,
    "card_number": "CORE-IT081",
    "language": "it",
    "pack_id": "41114006",
    "rarity_id": 1
  },
  {
    "card_count": 1,
    "card_id": 12033,
    "card_image_id": 1,
    "card_number": "CORE-IT082",
    "language": "it",
    "pack_id": "41114006",
    "rarity_id": 4
  },
  {
    "card_count": 1,
    "card_id": 12034,
    "card_image_id": 1,
    "card_number": "CORE-IT083",
    "language": "it",
    "pack_id": "41114006",
    "rarity_id": 3
  },
  {
    "card_count": 1,
    "card_id": 12035,
    "card_image_id": 1,
    "card_number": "CORE-IT084",
    "language": "it",
    "pack_id": "41114006",
    "rarity_id": 2
  },
  {
    "card_count": 1,
    "card_id": 12036,
    "card_image_id": 1,
    "card_number": "CORE-IT085",
    "language": "it",
    "pack_id": "41114006",
    "rarity_id": 2
  },
  {
    "card_count": 1,
    "card_id": 12037,
    "card_image_id": 1,
    "card_number": "CORE-IT086",
    "language": "it",
    "pack_id": "41114006",
    "rarity_id": 2
  },
  {
    "card_count": 1,
    "card_id": 12038,
    "card_image_id": 1,
    "card_number": "CORE-IT087",
    "language": "it",
    "pack_id": "41114006",
    "rarity_id": 2
  },
  {
    "card_count": 1,
    "card_id": 12039,
    "card_image_id": 1,
    "card_number": "CORE-IT088",
    "language": "it",
    "pack_id": "41114006",
    "rarity_id": 2
  },
  {
    "card_count": 1,
    "card_id": 12040,
    "card_image_id": 1,
    "card_number": "CORE-IT089",
    "language": "it",
    "pack_id": "41114006",
    "rarity_id": 1
  }
]