[
  {
    "card_count": 1,
    "card_id": 4989,
    "card_image_id": 1,
    "card_number": "SR02-IT039",
    "language": "it",
    "pack_id": "44412001",
    "rarity_id": 1
  },
  {
    "card_count": 1,
    "card_id": 5236,
    "card_image_id": 1,
    "card_number": "SR02-IT029",
    "language": "it",
    "pack_id": "44412001",
    "rarity_id": 1
  },
  {
    "card_count": 1,
    "card_id": 5328,
    "card_image_id": 1,
    "card_number": "SR02-IT031",
    "language": "it",
    "pack_id": "44412001",
    "rarity_id": 1
  },
  {
    "card_count": 1,
    "card_id": 5330,
    "card_image_id": 1,
    "card_number": "SR02-IT032",
    "language": "it",
    "pack_id": "44412001",
    "rarity_id": 1
  },
  {
    "card_count": 1,
    "card_id": 5343,
    "card_image_id": 1,
    "card_number": "SR02-IT027",
    "language": "it",
    "pack_id": "44412001",
    "rarity_id": 1
  },
  {
    "card_count": 1,
    "card_id": 5348,
    "card_image_id": 1,
    "card_number": "SR02-IT036",
    "language": "it",
    "pack_id": "44412001",
    "rarity_id": 1
  },
  {
    "card_count": 1,
    "card_id": 5537,
    "card_image_id": 1,
    "card_number": "SR02-IT034",
    "language": "it",
    "pack_id": "44412001",
    "rarity_id": 1
  },
  {
    "card_count": 1,
    "card_id": 6939,
    "card_image_id": 1,
    "card_number": "SR02-IT023",
    "language": "it",
    "pack_id": "44412001",
    "rarity_id": 1
  },
  {
    "card_count": 1,
    "card_id": 7244,
    "card_image_id": 1,
    "card_number": "SR02-IT005",
    "language": "it",
    "pack_id": "44412001",
    "rarity_id": 1
  },
  {
    "card_count": 1,
    "card_id": 7245,
    "card_image_id": 1,
    "card_number": "SR02-IT006",
    "language": "it",
    "pack_id": "44412001",
    "rarity_id": 1
  },
  {
    "card_count": 1,
    "card_id": 7246,
    "card_image_id": 1,
    "card_number": "SR02-IT007",
    "language": "it",
    "pack_id": "44412001",
    "rarity_id": 1
  },
  {
    "card_count": 1,
    "card_id": 7247,
    "card_image_id": 1,
    "card_number": "SR02-IT008",
    "language": "it",
    "pack_id": "44412001",
    "rarity_id": 1
  },
  {
    "card_count": 1,
    "card_id": 7248,
    "card_image_id": 1,
    "card_number": "SR02-IT028",
    "language": "it",
    "pack_id": "44412001",
    "rarity_id": 1
  },
  {
    "card_count": 1,
    "card_id": 7343,
    "card_image_id": 1,
    "card_number": "SR02-IT011",
    "language": "it",
    "pack_id": "44412001",
    "rarity_id": 1
  },
  {
    "card_count": 1,
    "card_id": 7389,
    "card_image_id": 1,
    "card_number": "SR02-IT030",
    "language": "it",
    "pack_id": "44412001",
    "rarity_id": 1
  },
  {
    "card_count": 1,
    "card_id": 7557,
    "card_image_id": 1,
    "card_number": "SR02-IT009",
    "language": "it",
    "pack_id": "44412001",
    "rarity_id": 1
  },
  {
    "card_count": 1,
    "card_id": 7591,
    "card_image_id": 1,
    "card_number": "SR02-IT020",
    "language": "it",
    "pack_id": "44412001",
    "rarity_id": 1
  },
  {
    "card_count": 1,
    "card_id": 7769,
    "card_image_id": 1,
    "card_number": "SR02-IT037",
    "language": "it",
    "pack_id": "44412001",
    "rarity_id": 1
  },
  {
    "card_count": 1,
    "card_id": 7797,
    "card_image_id": 1,
    "card_number": "SR02-IT021",
    "language": "it",
    "pack_id": "44412001",
    "rarity_id": 1
  },
  {
    "card_count": 1,
    "card_id": 7868,
    "card_image_id": 1,
    "card_number": "SR02-IT033",
    "language": "it",
    "pack_id": "44412001",
    "rarity_id": 1
  },
  {
    "card_count": 1,
    "card_id": 7982,
    "card_image_id": 1,
    "card_number": "SR02-IT010",
    "language": "it",
    "pack_id": "44412001",
    "rarity_id": 1
  },
  {
    "card_count": 1,
    "card_id": 9049,
    "card_image_id": 1,
    "card_number": "SR02-IT026",
    "language": "it",
    "pack_id": "44412001",
    "rarity_id": 1
  },
  {
    "card_count": 1,
    "card_id": 9814,
    "card_image_id": 1,
    "card_number": "SR02-IT014",
    "language": "it",
    "pack_id": "44412001",
    "rarity_id": 1
  },
  {
    "card_count": 1,
    "card_id": 9911,
    "card_image_id": 1,
    "card_number": "SR02-IT012",
    "language": "it",
    "pack_id": "44412001",
    "rarity_id": 1
  },
  {
    "card_count": 1,
    "card_id": 9957,
    "card_image_id": 1,
    "card_number": "SR02-IT015",
    "language": "it",
    "pack_id": "44412001",
    "rarity_id": 1
  },
  {
    "card_count": 1,
    "card_id": 9959,
    "card_image_id": 1,
    "card_number": "SR02-IT035",
    "language": "it",
    "pack_id": "44412001",
    "rarity_id": 1
  },
  {
    "card_count": 1,
    "card_id": 10437,
    "card_image_id": 1,
    "card_number": "SR02-IT038",
    "language": "it",
    "pack_id": "44412001",
    "rarity_id": 1
  },
  {
    "card_count": 1,
    "card_id": 10458,
    "card_image_id": 1,
    "card_number": "SR02-IT016",
    "language": "it",
    "pack_id": "44412001",
    "rarity_id": 1
  },
  {
    "card_count": 1,
    "card_id": 10459,
    "card_image_id": 1,
    "card_number": "SR02-IT019",
    "language": "it",
    "pack_id": "44412001",
    "rarity_id": 1
  },
  {
    "card_count": 1,
    "card_id": 10463,
    "card_image_id": 1,
    "card_number": "SR02-IT017",
    "language": "it",
    "pack_id": "44412001",
    "rarity_id": 1
  },
  {
    "card_count": 1,
    "card_id": 10743,
    "card_image_id": 1,
    "card_number": "SR02-IT013",
    "language": "it",
    "pack_id": "44412001",
    "rarity_id": 1
  },
  {
    "card_count": 1,
    "card_id": 10886,
    "card_image_id": 1,
    "card_number": "SR02-IT022",
    "language": "it",
    "pack_id": "44412001",
    "rarity_id": 1
  },
  {
    "card_count": 1,
    "card_id": 11409,
    "card_image_id": 1,
    "card_number": "SR02-IT040",
    "language": "it",
    "pack_id": "44412001",
    "rarity_id": 1
  },
  {
    "card_count": 1,
    "card_id": 11808,
    "card_image_id": 1,
    "card_number": "SR02-IT018",
    "language": "it",
    "pack_id": "44412001",
    "rarity_id": 1
  },
  {
    "card_count": 1,
    "card_id": 12359,
    "card_image_id": 1,
    "card_number": "SR02-IT000",
    "language": "it",
    "pack_id": "44412001",
    "rarity_id": 4
  },
  {
    "card_count": 1,
    "card_id": 12360,
    "card_image_id": 1,
    "card_number": "SR02-IT001",
    "language": "it",
    "pack_id": "44412001",
    "rarity_id": 4
  },
  {
    "card_count": 1,
    "card_id": 12361,
    "card_image_id": 1,
    "card_number": "SR02-IT003",
    "language": "it",
    "pack_id": "44412001",
    "rarity_id": 1
  },
  {
    "card_count": 1,
    "card_id": 12362,
    "card_image_id": 1,
    "card_number": "SR02-IT004",
    "language": "it",
    "pack_id": "44412001",
    "rarity_id": 1
  },
  {
    "card_count": 1,
    "card_id": 12363,
    "card_image_id": 1,
    "card_number": "SR02-IT024",
    "language": "it",
    "pack_id": "44412001",
    "rarity_id": 3
  },
  {
    "card_count": 1,
    "card_id": 12364,
    "card_image_id": 1,
    "card_number": "SR02-IT025",
    "language": "it",
    "pack_id": "44412001",
    "rarity_id": 3
  },
  {
    "card_count": 1,
    "card_id": 12382,
    "card_image_id": 1,
    "card_number": "SR02-IT002",
    "language": "it",
    "pack_id": "44412001",
    "rarity_id": 3
  }
]