{
  "attack_power": "3300",
  "attribute_id": 5,
  "card_id": 12152,
  "card_name": "Imperatore Goyo",
  "card_name_label": "",
  "card_name_search": "",
  "card_pen_effect": "",
  "card_text": "2 Mostri Synchro TERRA di Tipo Guerriero$NQuando questa carta, o un mostro che controlli che appartiene al tuo avversario, distrugge un mostro dell'avversario in battaglia e lo manda al Cimitero: puoi Evocare Specialmente quel mostro sul tuo Terreno. Quando il tuo avversario Evoca Specialmente uno o più mostri, eccetto durante il Damage Step: puoi offrire come Tributo 1 Mostro Synchro TERRA di Tipo Guerriero; prendi il controllo di quei mostri. Se questa carta scoperta lascia il Terreno: fai ritornare tutti i mostri che controlli sotto il controllo del loro proprietario.",
  "defense_power": "2500",
  "effect_id": 0,
  "language": "it",
  "legend_type": "",
  "linkmarker": "",
  "linkno": "",
  "min_card_image_id": 1,
  "note": "",
  "other_item_id": 3,
  "pen_scale_l": "",
  "pen_scale_r": "",
  "sales_at": "2016/01/14",
  "species_id": 15,
  "starchip": "10"
}