{
  "attack_power": "200",
  "attribute_id": 6,
  "card_id": 14567,
  "card_name": "Vespabattaglia - Ago il Bersaglio",
  "card_name_label": "",
  "card_name_search": "",
  "card_pen_effect": "",
  "card_text": "Se controlli un mostro Insetto: puoi Evocare Specialmente questa carta dalla tua mano. Durante la tua Main Phase: puoi infliggere al tuo avversario 200 danni per ogni \"Vespabattaglia - Ago il Bersaglio\" che controlli. Puoi utilizzare ogni effetto di \"Vespabattaglia - Ago il Bersaglio\" una sola volta per turno.",
  "defense_power": "300",
  "effect_id": 0,
  "language": "it",
  "legend_type": "",
  "linkmarker": "",
  "linkno": "",
  "note": "",
  "other_item_id": 1,
  "pen_scale_l": "",
  "pen_scale_r": "",
  "sales_at": "2019/07/11",
  "species_id": 10,
  "starchip": "1"
}