{
  "attack_power": "2000",
  "attribute_id": 2,
  "card_id": 16215,
  "card_name": "Diplomuomo del Master",
  "card_name_label": "",
  "card_name_search": "",
  "card_pen_effect": "",
  "card_text": "Se questa carta viene Evocata tramite Tributo: puoi scegliere come bersaglio 1 mostro nel tuo Cimitero e 1 mostro scoperto controllato dal tuo avversario; equipaggia il mostro dal tuo Cimitero a quel mostro dell'avversario. Mentre è equipaggiato da questo effetto, il mostro equipaggiato perde ATK pari all'ATK di quel mostro equipaggiato a esso. Il tuo avversario non può attivare gli effetti dei mostri che controlla che sono equipaggiati con Carte Equipaggiamento nelle tue Zone Magie & Trappole.",
  "defense_power": "2000",
  "effect_id": 0,
  "language": "it",
  "legend_type": "",
  "linkmarker": "",
  "linkno": "",
  "min_card_image_id": 1,
  "note": "",
  "other_item_id": 1,
  "pen_scale_l": "",
  "pen_scale_r": "",
  "sales_at": "2021/08/12",
  "species_id": 7,
  "starchip": "5"
}