{
  "attack_power": "0",
  "attribute_id": 8,
  "card_id": 18197,
  "card_name": "Creazione Numeron",
  "card_name_label": "",
  "card_name_search": "",
  "card_pen_effect": "",
  "card_text": "(Questa carta viene sempre considerata come una carta \"Occhi Galattici\", ma non come una carta \"Numero\".)$NSe 3 o più mostri LUCE Drago con ATK originale 3000 o superiore sono sul Terreno: Evoca Specialmente 1 Mostro Xyz \"Numero\" Drago dal tuo Extra Deck, poi attacca questa carta sul Terreno a esso come materiale. Puoi applicare questo effetto di \"Creazione Numeron\" una sola volta per turno.",
  "defense_power": "0",
  "effect_id": 0,
  "language": "it",
  "legend_type": "",
  "linkmarker": "",
  "linkno": "",
  "note": "",
  "other_item_id": 13,
  "pen_scale_l": "",
  "pen_scale_r": "",
  "sales_at": "2023/02/06",
  "species_id": 24,
  "starchip": "0"
}