{
  "attack_power": "1800",
  "attribute_id": 1,
  "card_id": 7674,
  "card_name": "Araldo della Perfezione",
  "card_name_label": "",
  "card_name_search": "",
  "card_pen_effect": "",
  "card_text": "Puoi Evocare tramite Rituale questa carta con \"Alba dell'Araldo\". Durante il turno di qualsiasi giocatore, quando il tuo avversario attiva una Carta Magia, Carta Trappola o l'effetto di un mostro: puoi mandare 1 mostro di Tipo Fata dalla tua mano al Cimitero; annulla l'attivazione e, se lo fai, distruggila.",
  "defense_power": "2800",
  "effect_id": 0,
  "language": "it",
  "legend_type": "",
  "linkmarker": "",
  "linkno": "",
  "note": "",
  "other_item_id": 5,
  "pen_scale_l": "",
  "pen_scale_r": "",
  "sales_at": "2010/05/06",
  "species_id": 17,
  "starchip": "6"
}