{
  "attack_power": "2510",
  "attribute_id": 1,
  "card_id": 10977,
  "card_name": "Numéro S39 : Première Utopie",
  "card_name_label": "",
  "card_name_search": "",
  "card_pen_effect": "",
  "card_text": "3 monstres LUMIÈRE de Niveau 4$NVous pouvez aussi Invoquer par Xyz cette carte en utilisant \"Numéro 39 : Utopie\" que vous contrôlez comme le Matériel Xyz. (Les Matériels Xyz attachés au monstre deviennent aussi des Matériels Xyz de cette carte.) Si votre adversaire a min. 3000 LP de plus que vous : vous pouvez détacher 3 Matériels Xyz de cette carte, et payez des LP jusqu'à n'en avoir plus que 10 ; détruisez autant de monstres Invoqués Spécialement contrôlés par votre adversaire que possible, et si vous le faites, bannissez-les, puis infligez 300 points de dommages à votre adversaire pour chaque monstre banni.",
  "defense_power": "2000",
  "effect_id": 0,
  "language": "fr",
  "legend_type": "",
  "linkmarker": "",
  "linkno": "",
  "min_card_image_id": 1,
  "note": "",
  "other_item_id": 23,
  "pen_scale_l": "",
  "pen_scale_r": "",
  "sales_at": "2015/05/14",
  "species_id": 15,
  "starchip": "4"
}