{
  "attack_power": "2600",
  "attribute_id": 3,
  "card_id": 12259,
  "card_name": "Numéro 37 : Espoir Tissé Dragon Araignée Requin",
  "card_name_label": "",
  "card_name_search": "",
  "card_pen_effect": "",
  "card_text": "2 monstres EAU de Niveau 4$NLorsque le monstre d'un joueur déclare une attaque : vous pouvez détacher 1 Matériel Xyz de cette carte ; jusqu'à la fin de ce tour, tous les monstres actuellement contrôlés par votre adversaire perdent 1000 ATK. Lorsque cette carte est détruite au combat ou par un effet de carte, et envoyée au Cimetière : vous pouvez cibler 1 autre monstre dans votre Cimetière ; Invoquez-le Spécialement. Vous ne pouvez utiliser chaque effet de \"Numéro 37 : Espoir Tissé Dragon Araignée Requin\" qu'une fois par tour.",
  "defense_power": "2100",
  "effect_id": 0,
  "language": "fr",
  "legend_type": "",
  "linkmarker": "",
  "linkno": "",
  "min_card_image_id": 1,
  "note": "",
  "other_item_id": 23,
  "pen_scale_l": "",
  "pen_scale_r": "",
  "sales_at": "2016/03/17",
  "species_id": 5,
  "starchip": "4"
}