{
  "attack_power": "0",
  "attribute_id": 9,
  "card_id": 12473,
  "card_name": "Pulsations Triamid",
  "card_name_label": "",
  "card_name_search": "",
  "card_pen_effect": "",
  "card_text": "Une fois par tour : vous pouvez bannir 2 cartes depuis votre Cimetière (toute combinaison de monstres de Type Rocher ou Cartes Magie de Terrain), puis activez 1 de ces effets ;$N●Ciblez 1 autre carte face recto sur le Terrain ; détruisez-la.$N●Ciblez 1 monstre de Type Rocher dans votre Cimetière ; Invoquez-le Spécialement en Position de Défense.$N●Ciblez max. 3 Cartes Magie de Terrain dans votre Cimetière ; mélangez-les dans le Deck, puis piochez 1 carte.",
  "defense_power": "0",
  "effect_id": 4,
  "language": "fr",
  "legend_type": "",
  "linkmarker": "",
  "linkno": "",
  "note": "",
  "other_item_id": 14,
  "pen_scale_l": "",
  "pen_scale_r": "",
  "sales_at": "2016/08/04",
  "species_id": 25,
  "starchip": "0"
}