{
  "attack_power": "2800",
  "attribute_id": 2,
  "card_id": 12628,
  "card_name": "Dragon Fusion Venin Affamé",
  "card_name_label": "",
  "card_name_search": "",
  "card_pen_effect": "",
  "card_text": "2 monstres TÉNÈBRES sur le Terrain (Jetons exclus)$NSi cette carte est Invoquée par Fusion : jusqu'à la fin de ce tour, vous pouvez faire gagner à cette carte une ATK égale à l'ATK d'1 monstre Invoqué Spécialement de l'adversaire. Une fois par tour : vous pouvez cibler 1 monstre de min. Niveau 5 contrôlé par votre adversaire ; jusqu'à la End Phase, le nom de cette carte devient le nom d'origine du monstre, et remplacez cet effet avec les effets d'origine du monstre. Si cette carte Invoquée par Fusion est détruite : vous pouvez détruire tous les monstres Invoqués Spécialement de votre adversaire.",
  "defense_power": "2000",
  "effect_id": 0,
  "language": "fr",
  "legend_type": "",
  "linkmarker": "",
  "linkno": "",
  "note": "",
  "other_item_id": 3,
  "pen_scale_l": "",
  "pen_scale_r": "",
  "sales_at": "2016/11/03",
  "species_id": 1,
  "starchip": "8"
}