{
  "attack_power": "0",
  "attribute_id": 8,
  "card_id": 15052,
  "card_name": "Avancée Lourde",
  "card_name_label": "",
  "card_name_search": "",
  "card_pen_effect": "",
  "card_text": "Lorsque cette carte est activée : vous pouvez ajouter 1 monstre \"Chenillinfini\" depuis votre Deck à votre main. Une fois par tour : vous pouvez cibler 1 Monstre Xyz Machine que vous contrôlez, puis activez 1 de ces effets ;$N●Changez sa position de combat.$N●Attachez-lui cette carte comme Matériel.$NVous ne pouvez activer qu'1 \"Avancée Lourde\" par tour.",
  "defense_power": "0",
  "effect_id": 4,
  "language": "fr",
  "legend_type": "0",
  "linkmarker": "",
  "linkno": "",
  "note": "",
  "other_item_id": 13,
  "pen_scale_l": "",
  "pen_scale_r": "",
  "sales_at": "2020/04/30",
  "species_id": 24,
  "starchip": "0"
}