{
  "attack_power": "3000",
  "attribute_id": 1,
  "card_id": 15524,
  "card_name": "Arsenal Divin AA-ZEUS - Tonnerre du Ciel",
  "card_name_label": "",
  "card_name_search": "",
  "card_pen_effect": "",
  "card_text": "2 monstres de Niveau 12$NUne fois par tour, si un Monstre Xyz a combattu ce tour, vous pouvez aussi Invoquer par Xyz \"Arsenal Divin AA-ZEUS - Tonnerre du Ciel\" en utilisant 1 Monstre Xyz que vous contrôlez comme Matériel. (Transférez ses Matériels à cette carte.) (Effet Rapide) : vous pouvez détacher 2 Matériels de cette carte ; envoyez toutes les autres cartes depuis le Terrain au Cimetière. Une fois par tour, si une ou plusieurs autres cartes que vous contrôlez sont détruites au combat ou par un effet de carte de l'adversaire : vous pouvez attacher 1 carte depuis votre main, Deck ou Extra Deck à cette carte comme Matériel.",
  "defense_power": "3000",
  "effect_id": 0,
  "language": "fr",
  "legend_type": "",
  "linkmarker": "",
  "linkno": "",
  "note": "",
  "other_item_id": 23,
  "pen_scale_l": "",
  "pen_scale_r": "",
  "sales_at": "2020/11/05",
  "species_id": 7,
  "starchip": "12"
}