{
  "attack_power": "1500",
  "attribute_id": 1,
  "card_id": 7829,
  "card_name": "Ver - Gurus",
  "card_name_label": "",
  "card_name_search": "",
  "card_pen_effect": "",
  "card_text": "Chaque fois qu'un monstre en Position de Défense face verso est retourné, placez 1 Compteur Ver sur cette carte. Cette carte gagne 300 points d'ATK pour chaque Compteur Ver sur elle.",
  "defense_power": "300",
  "effect_id": 0,
  "language": "fr",
  "legend_type": "",
  "linkmarker": "",
  "linkno": "",
  "note": "",
  "other_item_id": 1,
  "pen_scale_l": "",
  "pen_scale_r": "",
  "sales_at": "2010/06/17",
  "species_id": 20,
  "starchip": "4"
}