{
  "attack_power": "900",
  "attribute_id": 3,
  "card_id": 11935,
  "card_name": "Drachengruben-Magier",
  "card_name_label": "",
  "card_name_search": "",
  "card_pen_effect": "Einmal pro Spielzug, falls du eine „Magier“-Karte in deiner anderen Pendelzone hast: Du kannst 1 Pendelmonster abwerfen und dann 1 Zauber-/Fallenkarte auf dem Spielfeld wählen; zerstöre sie.",
  "card_text": "Dieser begabte Magier kann die in den auch Drachengruben genannten Tiefen der Erde verborgenen Energien erwecken. Aufgrund seiner stoischen Vorgehensweise hat er nur wenige Freunde, den Wünschen seines Schülers kommt er aber gern und oft nach.",
  "defense_power": "2700",
  "effect_id": 0,
  "language": "de",
  "legend_type": "",
  "linkmarker": "",
  "linkno": "",
  "min_card_image_id": 1,
  "note": "",
  "other_item_id": 25,
  "pen_scale_l": "8",
  "pen_scale_r": "8",
  "sales_at": "2015/12/03",
  "species_id": 18,
  "starchip": "7"
}