{
  "attack_power": "1500",
  "attribute_id": 5,
  "card_id": 14772,
  "card_name": "Dovelgus, Generaider-Boss des Eisens",
  "card_name_label": "",
  "card_name_search": "",
  "card_pen_effect": "",
  "card_text": "Du kannst nur 1 „Dovelgus, Generaider-Boss des Eisens“ kontrollieren. (Schnelleffekt): Du kannst eine beliebige Anzahl „Generaider“-Monster und/oder Maschine-Monster als Tribut anbieten; beschwöre genau so viele „Generaider“-Monster und/oder Maschine-Monster, alle mit unterschiedlichen Namen voneinander und den als Tribut angebotenen Monstern, als Spezialbeschwörung von deiner Hand in die Verteidigungsposition. Du kannst diesen Effekt von „Dovelgus, Generaider-Boss des Eisens“ nur einmal pro Spielzug verwenden.",
  "defense_power": "2500",
  "effect_id": 0,
  "language": "de",
  "legend_type": "",
  "linkmarker": "",
  "linkno": "",
  "min_card_image_id": 1,
  "note": "",
  "other_item_id": 1,
  "pen_scale_l": "",
  "pen_scale_r": "",
  "sales_at": "2019/11/21",
  "species_id": 7,
  "starchip": "9"
}