{
  "attack_power": "500",
  "attribute_id": 2,
  "card_id": 17452,
  "card_name": "Schreckensklaue Licht-Heart",
  "card_name_label": "",
  "card_name_search": "",
  "card_pen_effect": "",
  "card_text": "1 „Schreckensklaue“-Monster oder 1 „Visas Starfrost“$NFür die Linkbeschwörung dieser Karte kannst du nur Monster in deiner Main-Monsterzone als Material verwenden. Falls diese Karte als Linkbeschwörung in die Extra-Monsterzone beschworen wird: Du kannst deiner Hand 1 „Primitiver Planet Reichphobia“ von deinem Deck hinzufügen. Falls du „Visas Starfrost“ kontrollierst: Du kannst diese Karte als Spezialbeschwörung von deinem Friedhof beschwören. Du kannst diesen Effekt von „Schreckensklaue Licht-Heart“ nur einmal pro Duell verwenden.",
  "defense_power": "",
  "effect_id": 0,
  "language": "de",
  "legend_type": "",
  "linkmarker": "4",
  "linkno": "1",
  "note": "",
  "other_item_id": 43,
  "pen_scale_l": "",
  "pen_scale_r": "",
  "sales_at": "2022/08/04",
  "species_id": 12,
  "starchip": ""
}